maxcorr/__init__.py
maxcorr/typing.py
maxcorr/backends/__init__.py
maxcorr/backends/backend.py
maxcorr/backends/numpy.py
maxcorr/backends/tensorflow.py
maxcorr/backends/torch.py
maxcorr/indicators/__init__.py
maxcorr/indicators/density.py
maxcorr/indicators/gradient.py
maxcorr/indicators/indicator.py
maxcorr/indicators/kernel.py
maxcorr/indicators/randomized.py
maxcorr-0.1.2.dist-info/METADATA
maxcorr-0.1.2.dist-info/WHEEL
maxcorr-0.1.2.dist-info/licenses/LICENSE
maxcorr-0.1.2.dist-info/RECORD
