Metadata-Version: 2.4
Name: maxcorr
Version: 0.1.2
Summary: MaxCorr: A Package for Maximal Correlation Indicators
Project-URL: Repository, https://github.com/giuluck/maxcorr
Author: University of Bologna - DISI
Author-email: Luca Giuliani <luca.giuliani13@unibo.it>
Maintainer-email: Luca Giuliani <luca.giuliani13@unibo.it>
License-Expression: MIT
License-File: LICENSE
Classifier: Development Status :: 3 - Alpha
Classifier: License :: OSI Approved :: MIT License
Classifier: Operating System :: OS Independent
Classifier: Programming Language :: Python
Requires-Python: >=3.8
Requires-Dist: numpy>=1.24
Requires-Dist: pandas>=1.4
Requires-Dist: scikit-learn>=1.1
Requires-Dist: scipy>=1.10
Provides-Extra: full
Requires-Dist: tensorflow-lattice>=2.0.9; extra == 'full'
Requires-Dist: tensorflow>=2.13; extra == 'full'
Requires-Dist: torch>=1.12; extra == 'full'
Provides-Extra: lattice
Requires-Dist: tensorflow-lattice>=2.0.9; extra == 'lattice'
Requires-Dist: tensorflow>=2.13; extra == 'lattice'
Provides-Extra: tensorflow
Requires-Dist: tensorflow>=2.13; extra == 'tensorflow'
Provides-Extra: torch
Requires-Dist: torch>=1.12; extra == 'torch'
